{"labels": [10, 10, 10, 10, 2, 3, 4, 10, 10, 10, 10, 10, 1, 6, 10, 10, 10, 10, 10, 10, 1, 10, 10, 10, 10, 10, 10, 10, 10, 10, 10, 10, 1, 2, 3, 4, 7, 8, 10, 7, 10, 10, 10, 10, 0, 7, 10, 10, 10, 2, 3, 4, 10, 1, 10, 1, 10, 10, 10, 1, 19, 10, 10, 10, 1, 2, 3, 4, 6, 7, 8, 10, 11, 12, 19, 10, 1, 2, 3, 4, 10, 10, 10, 10, 2, 4, 10, 10, 2, 10, 10, 10, 10, 0, 1, 4, 6, 10, 11, 10], "scores": [0.0, 0.0, 0.0, 0.0, 0.0, 0.0, 0.0, 0.0, 0.0, 0.0, 0.0, 0.0, 0.0, 0.0, 0.0, 0.0, 0.0, 0.0, 0.0, 0.0, 0.0, 0.0, 0.0, 0.0, 0.0, 0.0, 0.0, 0.0, 0.0, 0.0, 0.0, 0.0, 0.0, 0.0, 0.0, 0.0, 0.0, 0.0, 0.0, 0.0, 0.0, 0.0, 0.0, 0.0, 0.0, 0.0, 0.0, 0.0, 0.0, 0.0, 0.0, 0.0, 0.0, 0.0, 0.0, 0.0, 0.0, 0.0, 0.0, 0.0005864378763362765, 0.8922275304794312, 0.0, 0.0, 0.0, 0.0, 0.0, 0.0, 0.0, 0.0, 0.0, 0.0, 0.0, 0.0, 0.0, 0.0, 0.0, 0.0, 0.0, 0.0, 0.0, 0.0, 0.0, 0.0, 0.0, 0.0, 0.0, 0.0, 0.0, 0.0, 0.0, 0.0, 0.0, 0.0, 0.0, 0.0, 0.0, 0.0, 0.0, 0.0, 0.0], "bboxes": [[0.0, 0.0, 0.0, 0.0], [0.0, 0.0, 0.0, 0.0], [0.0, 0.0, 0.0, 0.0], [0.0, 0.0, 0.0, 0.0], [0.0, 0.0, 0.0, 0.0], [0.0, 0.0, 0.0, 0.0], [0.0, 0.0, 0.0, 0.0], [0.0, 0.0, 0.0, 0.0], [0.0, 0.0, 0.0, 0.0], [0.0, 0.0, 0.0, 0.0], [0.0, 0.0, 0.0, 0.0], [0.0, 0.0, 0.0, 0.0], [0.0, 0.0, 0.0, 0.0], [0.0, 0.0, 0.0, 0.0], [0.0, 0.0, 0.0, 0.0], [0.0, 0.0, 0.0, 0.0], [0.0, 0.0, 0.0, 0.0], [0.0, 0.0, 0.0, 0.0], [0.0, 0.0, 0.0, 0.0], [0.0, 0.0, 0.0, 0.0], [0.0, 0.0, 0.0, 0.0], [0.0, 0.0, 0.0, 0.0], [0.0, 0.0, 0.0, 0.0], [0.0, 0.0, 0.0, 0.0], [0.0, 0.0, 0.0, 0.0], [0.0, 0.0, 0.0, 0.0], [0.0, 0.0, 0.0, 0.0], [0.0, 0.0, 0.0, 0.0], [0.0, 0.0, 0.0, 0.0], [0.0, 0.0, 0.0, 0.0], [0.0, 0.0, 0.0, 0.0], [0.0, 0.0, 0.0, 0.0], [0.0, 0.0, 0.0, 0.0], [0.0, 0.0, 0.0, 0.0], [0.0, 0.0, 0.0, 0.0], [0.0, 0.0, 0.0, 0.0], [0.0, 0.0, 0.0, 0.0], [0.0, 0.0, 0.0, 0.0], [0.0, 0.0, 0.0, 0.0], [0.0, 0.0, 0.0, 0.0], [0.0, 0.0, 0.0, 0.0], [0.0, 0.0, 0.0, 0.0], [0.0, 0.0, 0.0, 0.0], [0.0, 0.0, 0.0, 0.0], [0.0, 0.0, 0.0, 0.0], [0.0, 0.0, 0.0, 0.0], [0.0, 0.0, 0.0, 0.0], [0.0, 0.0, 0.0, 0.0], [0.0, 0.0, 0.0, 0.0], [0.0, 0.0, 0.0, 0.0], [0.0, 0.0, 0.0, 0.0], [0.0, 0.0, 0.0, 0.0], [0.0, 0.0, 0.0, 0.0], [0.0, 0.0, 0.0, 0.0], [0.0, 0.0, 0.0, 0.0], [0.0, 0.0, 0.0, 0.0], [0.0, 0.0, 0.0, 0.0], [0.0, 0.0, 0.0, 0.0], [0.0, 0.0, 0.0, 0.0], [416.0, 529.0, 1587.0, 1080.0], [416.0, 529.0, 1587.0, 1080.0], [0.0, 0.0, 0.0, 0.0], [0.0, 0.0, 0.0, 0.0], [0.0, 0.0, 0.0, 0.0], [0.0, 0.0, 0.0, 0.0], [0.0, 0.0, 0.0, 0.0], [0.0, 0.0, 0.0, 0.0], [0.0, 0.0, 0.0, 0.0], [0.0, 0.0, 0.0, 0.0], [0.0, 0.0, 0.0, 0.0], [0.0, 0.0, 0.0, 0.0], [0.0, 0.0, 0.0, 0.0], [0.0, 0.0, 0.0, 0.0], [0.0, 0.0, 0.0, 0.0], [0.0, 0.0, 0.0, 0.0], [0.0, 0.0, 0.0, 0.0], [0.0, 0.0, 0.0, 0.0], [0.0, 0.0, 0.0, 0.0], [0.0, 0.0, 0.0, 0.0], [0.0, 0.0, 0.0, 0.0], [0.0, 0.0, 0.0, 0.0], [0.0, 0.0, 0.0, 0.0], [0.0, 0.0, 0.0, 0.0], [0.0, 0.0, 0.0, 0.0], [0.0, 0.0, 0.0, 0.0], [0.0, 0.0, 0.0, 0.0], [0.0, 0.0, 0.0, 0.0], [0.0, 0.0, 0.0, 0.0], [0.0, 0.0, 0.0, 0.0], [0.0, 0.0, 0.0, 0.0], [0.0, 0.0, 0.0, 0.0], [0.0, 0.0, 0.0, 0.0], [0.0, 0.0, 0.0, 0.0], [0.0, 0.0, 0.0, 0.0], [0.0, 0.0, 0.0, 0.0], [0.0, 0.0, 0.0, 0.0], [0.0, 0.0, 0.0, 0.0], [0.0, 0.0, 0.0, 0.0], [0.0, 0.0, 0.0, 0.0], [0.0, 0.0, 0.0, 0.0]], "masks": [{"size": [1080, 1920], "counts": "PPYo1"}, {"size": [1080, 1920], "counts": "PPYo1"}, {"size": [1080, 1920], "counts": "PPYo1"}, {"size": [1080, 1920], "counts": "PPYo1"}, {"size": [1080, 1920], "counts": "PPYo1"}, {"size": [1080, 1920], "counts": "PPYo1"}, {"size": [1080, 1920], "counts": "PPYo1"}, {"size": [1080, 1920], "counts": "PPYo1"}, {"size": [1080, 1920], "counts": "PPYo1"}, {"size": [1080, 1920], "counts": "PPYo1"}, {"size": [1080, 1920], "counts": "PPYo1"}, {"size": [1080, 1920], "counts": "PPYo1"}, {"size": [1080, 1920], "counts": "PPYo1"}, {"size": [1080, 1920], "counts": "PPYo1"}, {"size": [1080, 1920], "counts": "PPYo1"}, {"size": [1080, 1920], "counts": "PPYo1"}, {"size": [1080, 1920], "counts": "PPYo1"}, {"size": [1080, 1920], "counts": "PPYo1"}, {"size": [1080, 1920], "counts": "PPYo1"}, {"size": [1080, 1920], "counts": "PPYo1"}, {"size": [1080, 1920], "counts": "PPYo1"}, {"size": [1080, 1920], "counts": "PPYo1"}, {"size": [1080, 1920], "counts": "PPYo1"}, {"size": [1080, 1920], "counts": "PPYo1"}, {"size": [1080, 1920], "counts": "PPYo1"}, {"size": [1080, 1920], "counts": "PPYo1"}, {"size": [1080, 1920], "counts": "PPYo1"}, {"size": [1080, 1920], "counts": "PPYo1"}, {"size": [1080, 1920], "counts": "PPYo1"}, {"size": [1080, 1920], "counts": "PPYo1"}, {"size": [1080, 1920], "counts": "PPYo1"}, {"size": [1080, 1920], "counts": "PPYo1"}, {"size": [1080, 1920], "counts": "PPYo1"}, {"size": [1080, 1920], "counts": "PPYo1"}, {"size": [1080, 1920], "counts": "PPYo1"}, {"size": [1080, 1920], "counts": "PPYo1"}, {"size": [1080, 1920], "counts": "PPYo1"}, {"size": [1080, 1920], "counts": "PPYo1"}, {"size": [1080, 1920], "counts": "PPYo1"}, {"size": [1080, 1920], "counts": "PPYo1"}, {"size": [1080, 1920], "counts": "PPYo1"}, {"size": [1080, 1920], "counts": "PPYo1"}, {"size": [1080, 1920], "counts": "PPYo1"}, {"size": [1080, 1920], "counts": "PPYo1"}, {"size": [1080, 1920], "counts": "PPYo1"}, {"size": [1080, 1920], "counts": "PPYo1"}, {"size": [1080, 1920], "counts": "PPYo1"}, {"size": [1080, 1920], "counts": "PPYo1"}, {"size": [1080, 1920], "counts": "PPYo1"}, {"size": [1080, 1920], "counts": "PPYo1"}, {"size": [1080, 1920], "counts": "PPYo1"}, {"size": [1080, 1920], "counts": "PPYo1"}, {"size": [1080, 1920], "counts": "PPYo1"}, {"size": [1080, 1920], "counts": "PPYo1"}, {"size": [1080, 1920], "counts": "PPYo1"}, {"size": [1080, 1920], "counts": "PPYo1"}, {"size": [1080, 1920], "counts": "PPYo1"}, {"size": [1080, 1920], "counts": "PPYo1"}, {"size": [1080, 1920], "counts": "PPYo1"}, {"size": [1080, 1920], "counts": "X[g=f0iP1`0E=C=SOZNSQOn1dn0l0G9F7J7J6J8H5L4K6K4K5FSK`SOR5[l09L3K6K4N3M2N2N2N3M4M1N2N3N2M2O2N1N2N2N2N3M4K4M3L4M3L2O2N3M2O1N3M2O0O2N2N2N2M3N2N3L3L3N3N3M2M2N3M4M3M2N1N3N2M3N1N4L2O101JPFaXOQ:]g07M2O2M3M3I^ESYOd:kf0_ESYOc:kf07N2N110O1O10O2O0OO2N101N1O2N1O2N1O1O2N1012M01OgDgYOR;Xf0nDhYOT;Vf0kDkYOV;Uf0iDkYOX;Uf0fDlYO[;Xf02N10000UOdDY[Od0YOQ:\\e0\\EZ[Oc0[OQ:[e0[EZ[O`;ed0_DZ[Oc0[OZ:Ze0SEZ[Oc0]O[:oe0eERZO[:me0dEZZOW:fe0hE[ZOY:ee0eE\\ZO[:ce0eE]ZO\\:`e0fE`ZO[:^e0fEbZO[:\\e0fE^ZO\\OOo:be0eE^ZO^ONo:ce0dE\\ZO@0n:ce0P1O1O2N1OeDbZO]:]e0cEdZO]:[e0cEeZO^:[e0aEfZO_:Ze0_EgZOb:Ye0]EhZOc:Xe0\\EhZOe:We0[EiZOg:Te0YElZOi:Se0WEmZOj:Se0TEnZOm:Qe0SEoZOn:Qe0QEnZOR;Qe0mDoZOT;Qe0kDP[OU;od0lDP[OU;od0lDQ[OT;od0kDQ[OV;od0jDP[OW;Pe0gDQ[O[;nd0dDQ[O^;nd0bDR[O_;nd0`DQ[Ob;nd0_DP[Od;nd0d0O1O1O1O1O1O1O001O1O10O3N0VD\\[O_:dd0_E^[Oa:bd0cD[[OOM86IMR;ed0kD^[O0K98G0Q;jd0oDoZO88GOS;jd0lDP[O3MOi0S;ad0lDf[OU;]e0ZGfYOQ6Yf0aGcYOU29Y6Tf0bGdYOR2;kMG\\8Yf0kIZZOU6ee0gI`ZOY6^e0eIhZOY6Xe0eIlZOY6Te0fInZOY6Re0fIP[OY6Pe0fIQ[OZ6od0dIR[O\\6nd0cIT[O]6ld0aIV[O_6jd0_IX[Oa6gd0^I\\[Oa6cd0^I_[Ob6ad0\\Ia[Od6^d0[Ie[OcNVNk7Tf0bIo[O\\6Pd0bIU\\O\\6ic0dIZ\\O[6ec0dI\\\\O]6cc0bI_\\O^6cc0^I^\\Oc6bc0ZI`\\Og6`c0PIoYOXOe20\\M^7Pf0YIoYOXOg2O\\M_7me0[IPZOXOn2^7Qc0aIP]O_6nb0bIR]O_6mb0aIT]O_6kb0^IX]Ob6ib0UIUZO[OT3`7fb0TIXZOZOV3`7ab0VIYZOYOX3a7^b0VIj]Oi6Ub0VIn]Oi6Rb0VIP^Oi6oa0VIT^Oi6ka0SIa^Of6^a0XId^Oi6[a0VIg^Oj6Ya0iH]ZO8e4d6Sa0[Io^O5XKP6he0jIT_O2XKR6ce0lIW_O0WKS6be0mIg_OR6Y`0lIk_OR6U`0kIQ@R6me0N001aJYTOi4hk0UKZTOk4gk0RKaTOh4`k0UKaTOl4_k0RKcTOn4]k0PKeTOo4\\k0oJgTOP5Zk0mJgTOT5ok00O0010O010O01000O010O10000O10O1O1O010O100O100O1O001O1O010O1O001O0O2N101O1N2O001O1O001N1O2O1N2O001O001O000010O00001O00001O1O000000000000000000001O00000000O100O1O1N2L4002N2N1O00001O001O001O1O0000NWJWTOg5fk0[J\\TOd5dk0\\J\\TOd5ek0[J[TOe5fk0ZJZTOf5fk0ZJZTOf5fk0[JYTOe5gk0[JYTOe5hk0ZJWTOg5ik0YJWTOg5lk0100000000001O00001O001O00000000000000000000001O001O3M4L2N2N1O2N00O100000000000000000000000000000000000000KhJjSOX5Vl0jJgSOW5Yl0400000000001O001O0000O100O1O100O1O1000000000000000000O10000O100N2O1O10000000000001dJPTOK0k4Pl0YKSTOH0n4Rl0TKWTOk4\\l0O00O100O1001O00001O1O1O1O001O00001O001O1O001O000000000000000000O10000O100O100000000O10000CWKkSOi4bl00000000000000001O00001O001O00000000001O2N2N1O00O1M3O1001O001O0000001O00O100O10000O10000001O1O000000000000000000O1O100O100O1N2O11O000000000000O1000000001O000000O100O10000O10000001O0000002N1O001O001O002N1O1O000000O1001O00000000000000001O00001O000000000000000000000000O100O10000O100O100O100O1O1O100O100O100O1O1O1O100O1O1O100N2N2O1000000O100000000O10000000000000000O100001O1O001O1O1O001O001O2N0000001O000000001O00001O00O1O1O100O10000O1O1O1KnJcSOS5\\l05000000000000O1001O000000000000001O001O1O001O001O1O2N1O0000000000000000O1O1O1O1001O001O0000O100O1O100O10000000000000000000000O10000000000O100O100O100O100O10000O100000000O10000O100O100O10000O1000000O100000000O100000000001O0000O100O100000000000000O1000000O100O100O10000000000O100O1000000O10O10O10O100000001O0O10000000O01000001N1000O10O01000O100O100O100O100O10O0100O1O10O010L300100O010O00K^JUTOb5kk06O00001O0010O010O1O10O000^OXJjTO13h5Rk0aJlTO_5Uk0aJjTO_5Vk0b0L300100OMaIoTO_6oj051O10KbISUOZ6ij0kIVUOU6gj0`0N1WOQIiVOP7Xi0RIeVOn6\\i0SIWVO01l6ii0VIRVO13j6ki0`ISVO`6mi0e0100O1O100O1O001O1O1O100O1O1O1O0010O01O1O1O1O2O0O1O1O1O1O1O100O001O1O1O1O001O0000001O001O00010O001O1O100O00001O1O1O010O001O1O100O1O1O1O1O0O2O001N101O001OO1K40100001O_OPJ[UOP6ej0RJYUOm5gj0VJXUOi5hj0XJWUOh5ij0YJWUOf5hj0e0O02O001N010O10000O100000000000M210001O000000000O100O1000O0M4O1M2M40O100O10O02O000O1O100O00010O1O101N100O0010O010N100^OWIPVOP7Pj0VIkUOj6Uj0;1OM41N010O01N2M201L3O2OOK6ZOUHbWOk7^h0WHRWON8i7hh0ZHmVO0:d7ih0eHXWOX7ih0jHXWOR7jh0nHlVOB4^7Si0oHgVOE5Z7Xi0QIbVOF4Y7[i0WIeVOg6]i0YIcVOd6_i0^I_VOa6ai0j0LoGdVOP8]i0SH`VOl7bi024MNRH^VOk7di0XHZVOf7hi031N2O1O1N3N1N3M3N3L3M4M2L5M2M3M3N3L5L3L4M2M4M2M4L3M4M2M3L5L3K5L3O1N2N2N2O2M2O2L3O2M3M4F:G9B>H:H:\\MmPOQ2QP1YOa0B:@Wdn:"}, {"size": [1080, 1920], "counts": "X[g=f0iP1`0E=C=SOZNSQOn1dn0l0G9F7J7J6J8H5L4K6K4K5FSK`SOR5[l09L3K6K4N3M2N2N2N3M4M1N2N3N2M2O2N1N2N2N2N3M4K4M3L4M3L2O2N3M2O1N3M2O0O2N2N2N2M3N2N3L3L3N3N3M2M2N3M4M3M2N1N3N2M3N1N4L2O101JPFaXOQ:]g07M2O2M3M3I^ESYOd:kf0_ESYOc:kf07N2N110O1O10O2O0OO2N101N1O2N1O2N1O1O2N1012M01OgDgYOR;Xf0nDhYOT;Vf0kDkYOV;Uf0iDkYOX;Uf0fDlYO[;Xf02N10000UOdDY[Od0YOQ:\\e0\\EZ[Oc0[OQ:[e0[EZ[O`;ed0_DZ[Oc0[OZ:Ze0SEZ[Oc0]O[:oe0eERZO[:me0dEZZOW:fe0hE[ZOY:ee0eE\\ZO[:ce0eE]ZO\\:`e0fE`ZO[:^e0fEbZO[:\\e0fE^ZO\\OOo:be0eE^ZO^ONo:ce0dE\\ZO@0n:ce0P1O1O2N1OeDbZO]:]e0cEdZO]:[e0cEeZO^:[e0aEfZO_:Ze0_EgZOb:Ye0]EhZOc:Xe0\\EhZOe:We0[EiZOg:Te0YElZOi:Se0WEmZOj:Se0TEnZOm:Qe0SEoZOn:Qe0QEnZOR;Qe0mDoZOT;Qe0kDP[OU;od0lDP[OU;od0lDQ[OT;od0kDQ[OV;od0jDP[OW;Pe0gDQ[O[;nd0dDQ[O^;nd0bDR[O_;nd0`DQ[Ob;nd0_DP[Od;nd0d0O1O1O1O1O1O1O001O1O10O3N0VD\\[O_:dd0_E^[Oa:bd0cD[[OOM86IMR;ed0kD^[O0K98G0Q;jd0oDoZO88GOS;jd0lDP[O3MOi0S;ad0lDf[OU;]e0ZGfYOQ6Yf0aGcYOU29Y6Tf0bGdYOR2;kMG\\8Yf0kIZZOU6ee0gI`ZOY6^e0eIhZOY6Xe0eIlZOY6Te0fInZOY6Re0fIP[OY6Pe0fIQ[OZ6od0dIR[O\\6nd0cIT[O]6ld0aIV[O_6jd0_IX[Oa6gd0^I\\[Oa6cd0^I_[Ob6ad0\\Ia[Od6^d0[Ie[OcNVNk7Tf0bIo[O\\6Pd0bIU\\O\\6ic0dIZ\\O[6ec0dI\\\\O]6cc0bI_\\O^6cc0^I^\\Oc6bc0ZI`\\Og6`c0PIoYOXOe20\\M^7Pf0YIoYOXOg2O\\M_7me0[IPZOXOn2^7Qc0aIP]O_6nb0bIR]O_6mb0aIT]O_6kb0^IX]Ob6ib0UIUZO[OT3`7fb0TIXZOZOV3`7ab0VIYZOYOX3a7^b0VIj]Oi6Ub0VIn]Oi6Rb0VIP^Oi6oa0VIT^Oi6ka0SIa^Of6^a0XId^Oi6[a0VIg^Oj6Ya0iH]ZO8e4d6Sa0[Io^O5XKP6he0jIT_O2XKR6ce0lIW_O0WKS6be0mIg_OR6Y`0lIk_OR6U`0kIQ@R6me0N001aJYTOi4hk0UKZTOk4gk0RKaTOh4`k0UKaTOl4_k0RKcTOn4]k0PKeTOo4\\k0oJgTOP5Zk0mJgTOT5ok00O0010O010O01000O010O10000O10O1O1O010O100O100O1O001O1O010O1O001O0O2N101O1N2O001O1O001N1O2O1N2O001O001O000010O00001O00001O1O000000000000000000001O00000000O100O1O1N2L4002N2N1O00001O001O001O1O0000NWJWTOg5fk0[J\\TOd5dk0\\J\\TOd5ek0[J[TOe5fk0ZJZTOf5fk0ZJZTOf5fk0[JYTOe5gk0[JYTOe5hk0ZJWTOg5ik0YJWTOg5lk0100000000001O00001O001O00000000000000000000001O001O3M4L2N2N1O2N00O100000000000000000000000000000000000000KhJjSOX5Vl0jJgSOW5Yl0400000000001O001O0000O100O1O100O1O1000000000000000000O10000O100N2O1O10000000000001dJPTOK0k4Pl0YKSTOH0n4Rl0TKWTOk4\\l0O00O100O1001O00001O1O1O1O001O00001O001O1O001O000000000000000000O10000O100O100000000O10000CWKkSOi4bl00000000000000001O00001O001O00000000001O2N2N1O00O1M3O1001O001O0000001O00O100O10000O10000001O1O000000000000000000O1O100O100O1N2O11O000000000000O1000000001O000000O100O10000O10000001O0000002N1O001O001O002N1O1O000000O1001O00000000000000001O00001O000000000000000000000000O100O10000O100O100O100O1O1O100O100O100O1O1O1O100O1O1O100N2N2O1000000O100000000O10000000000000000O100001O1O001O1O1O001O001O2N0000001O000000001O00001O00O1O1O100O10000O1O1O1KnJcSOS5\\l05000000000000O1001O000000000000001O001O1O001O001O1O2N1O0000000000000000O1O1O1O1001O001O0000O100O1O100O10000000000000000000000O10000000000O100O100O100O100O10000O100000000O10000O100O100O10000O1000000O100000000O100000000001O0000O100O100000000000000O1000000O100O100O10000000000O100O1000000O10O10O10O100000001O0O10000000O01000001N1000O10O01000O100O100O100O100O10O0100O1O10O010L300100O010O00K^JUTOb5kk06O00001O0010O010O1O10O000^OXJjTO13h5Rk0aJlTO_5Uk0aJjTO_5Vk0b0L300100OMaIoTO_6oj051O10KbISUOZ6ij0kIVUOU6gj0`0N1WOQIiVOP7Xi0RIeVOn6\\i0SIWVO01l6ii0VIRVO13j6ki0`ISVO`6mi0e0100O1O100O1O001O1O1O100O1O1O1O0010O01O1O1O1O2O0O1O1O1O1O1O100O001O1O1O1O001O0000001O001O00010O001O1O100O00001O1O1O010O001O1O100O1O1O1O1O0O2O001N101O001OO1K40100001O_OPJ[UOP6ej0RJYUOm5gj0VJXUOi5hj0XJWUOh5ij0YJWUOf5hj0e0O02O001N010O10000O100000000000M210001O000000000O100O1000O0M4O1M2M40O100O10O02O000O1O100O00010O1O101N100O0010O010N100^OWIPVOP7Pj0VIkUOj6Uj0;1OM41N010O01N2M201L3O2OOK6ZOUHbWOk7^h0WHRWON8i7hh0ZHmVO0:d7ih0eHXWOX7ih0jHXWOR7jh0nHlVOB4^7Si0oHgVOE5Z7Xi0QIbVOF4Y7[i0WIeVOg6]i0YIcVOd6_i0^I_VOa6ai0j0LoGdVOP8]i0SH`VOl7bi024MNRH^VOk7di0XHZVOf7hi031N2O1O1N3N1N3M3N3L3M4M2L5M2M3M3N3L5L3L4M2M4M2M4L3M4M2M3L5L3K5L3O1N2N2N2O2M2O2L3O2M3M4F:G9B>H:H:\\MmPOQ2QP1YOa0B:@Wdn:"}, {"size": [1080, 1920], "counts": "PPYo1"}, {"size": [1080, 1920], "counts": "PPYo1"}, {"size": [1080, 1920], "counts": "PPYo1"}, {"size": [1080, 1920], "counts": "PPYo1"}, {"size": [1080, 1920], "counts": "PPYo1"}, {"size": [1080, 1920], "counts": "PPYo1"}, {"size": [1080, 1920], "counts": "PPYo1"}, {"size": [1080, 1920], "counts": "PPYo1"}, {"size": [1080, 1920], "counts": "PPYo1"}, {"size": [1080, 1920], "counts": "PPYo1"}, {"size": [1080, 1920], "counts": "PPYo1"}, {"size": [1080, 1920], "counts": "PPYo1"}, {"size": [1080, 1920], "counts": "PPYo1"}, {"size": [1080, 1920], "counts": "PPYo1"}, {"size": [1080, 1920], "counts": "PPYo1"}, {"size": [1080, 1920], "counts": "PPYo1"}, {"size": [1080, 1920], "counts": "PPYo1"}, {"size": [1080, 1920], "counts": "PPYo1"}, {"size": [1080, 1920], "counts": "PPYo1"}, {"size": [1080, 1920], "counts": "PPYo1"}, {"size": [1080, 1920], "counts": "PPYo1"}, {"size": [1080, 1920], "counts": "PPYo1"}, {"size": [1080, 1920], "counts": "PPYo1"}, {"size": [1080, 1920], "counts": "PPYo1"}, {"size": [1080, 1920], "counts": "PPYo1"}, {"size": [1080, 1920], "counts": "PPYo1"}, {"size": [1080, 1920], "counts": "PPYo1"}, {"size": [1080, 1920], "counts": "PPYo1"}, {"size": [1080, 1920], "counts": "PPYo1"}, {"size": [1080, 1920], "counts": "PPYo1"}, {"size": [1080, 1920], "counts": "PPYo1"}, {"size": [1080, 1920], "counts": "PPYo1"}, {"size": [1080, 1920], "counts": "PPYo1"}, {"size": [1080, 1920], "counts": "PPYo1"}, {"size": [1080, 1920], "counts": "PPYo1"}, {"size": [1080, 1920], "counts": "PPYo1"}, {"size": [1080, 1920], "counts": "PPYo1"}, {"size": [1080, 1920], "counts": "PPYo1"}, {"size": [1080, 1920], "counts": "PPYo1"}]}